[
    {
        "direction": "vertical",
        "clue_number": "15",
        "clues": [
            {
                "clue_1)": "مُعاتبة النّفْس ومُراقبتها"
            },
            {
                "clue_2)": "مَن يبيع الأدوية والعقاقير"
            },
            {
                "clue_3)": "عملة آسيوية"
            }
        ]
    },
    {
        "direction": "vertical",
        "clue_number": "14",
        "clues": [
            {
                "clue_1)": "ظهرَ الهلال"
            },
            {
                "clue_2)": "يَتْبع"
            },
            {
                "clue_3)": "عاصمة استراليا"
            }
        ]
    },
    {
        "direction": "vertical",
        "clue_number": "13",
        "clues": [
            {
                "clue_1)": "اللقب الذي أطلقه الرسول صلّى الله عليه وسلّم على أبي عبيدة"
            },
            {
                "clue_3)": "عكس فَرَح"
            }
        ]
    },
    {
        "direction": "vertical",
        "clue_number": "12",
        "clues": [
            {
                "clue_1)": "شركة أمريكية متخصصة في صناعة السيارات الكهربائية"
            },
            {
                "clue_2)": "سكنَ , أقامَ"
            },
            {
                "clue_3)": "فسيح"
            }
        ]
    },
    {
        "direction": "vertical",
        "clue_number": "11",
        "clues": [
            {
                "clue_1)": "اقتراب"
            },
            {
                "clue_2)": "جَسَد"
            },
            {
                "clue_3)": "جارى , ماشى"
            },
            {
                "clue_4)": "أحد الأطراف"
            }
        ]
    },
    {
        "direction": "vertical",
        "clue_number": "10",
        "clues": [
            {
                "clue_1)": "دولة إفريقية اسمها يعني الحرية"
            },
            {
                "clue_2)": "ينتمي إلى دولة أوروبية عاصمتها لشبونة"
            }
        ]
    },
    {
        "direction": "vertical",
        "clue_number": "9",
        "clues": [
            {
                "clue_1)": "مُخلِص وفي"
            },
            {
                "clue_2)": "علم مذكر معناه : كل ما يُنتفع به"
            },
            {
                "clue_3)": "حرف موسيقي"
            },
            {
                "clue_4)": "للنهي"
            }
        ]
    },
    {
        "direction": "vertical",
        "clue_number": "8",
        "clues": [
            {
                "clue_1)": "نبات أزهاره جميلة ورائحته طيبة (معكوسة)"
            },
            {
                "clue_2)": "من أنواع الطيور"
            },
            {
                "clue_3)": "مدينة إسبانية يقع فيها قصر الحمراء"
            }
        ]
    },
    {
        "direction": "vertical",
        "clue_number": "7",
        "clues": [
            {
                "clue_1)": "حرفان مكرران"
            },
            {
                "clue_2)": "أكبر جزيرة في اليابان"
            },
            {
                "clue_3)": "جَزّار"
            }
        ]
    },
    {
        "direction": "vertical",
        "clue_number": "6",
        "clues": [
            {
                "clue_1)": "يقنط"
            },
            {
                "clue_2)": "الاسم الأول لقاض ٍ اشتهر بالذكاء"
            },
            {
                "clue_3)": "يُدرك , يفهم"
            }
        ]
    },
    {
        "direction": "vertical",
        "clue_number": "5",
        "clues": [
            {
                "clue_1)": "الاسم الثاني للاعب كرة قدم ألماني (معكوسة)"
            },
            {
                "clue_2)": "ممثلة مصرية راحلة من أبرز أعمالها مسرحية العيال كبرت"
            }
        ]
    },
    {
        "direction": "vertical",
        "clue_number": "4",
        "clues": [
            {
                "clue_1)": "للنداء"
            },
            {
                "clue_2)": "الاعتماد"
            },
            {
                "clue_3)": "عمَّت، شاعت"
            }
        ]
    },
    {
        "direction": "vertical",
        "clue_number": "3",
        "clues": [
            {
                "clue_1)": "حساب الزمن بالسنين والشهور والأيام"
            },
            {
                "clue_2)": "شتمَ (معكوسة)"
            },
            {
                "clue_3)": "رونالد ...... لاعب كرة قدم من أوروغواي يلعب مدافعًا لنادي برشلونة"
            }
        ]
    },
    {
        "direction": "vertical",
        "clue_number": "2",
        "clues": [
            {
                "clue_1)": "بَيْت مِنْ قَصَبٍ أَوْ قَشٍّ"
            },
            {
                "clue_2)": "أكبر مدن جنوب أفريقيا"
            }
        ]
    },
    {
        "direction": "vertical",
        "clue_number": "1",
        "clues": [
            {
                "clue_1)": "أعظم قياصرة روسيا"
            },
            {
                "clue_2)": "اسم موصول"
            }
        ]
    },
    {
        "direction": "horizontal",
        "clue_number": "1",
        "clues": [
            {
                "clue_1)": "كائنات مجهرية ذات خلية واحدة بعضها مُفيد والبعض الآخر ضار"
            },
            {
                "clue_2)": "عملة عربية ( بصيغة الجمع )"
            }
        ]
    },
    {
        "direction": "horizontal",
        "clue_number": "2",
        "clues": [
            {
                "clue_1)": "اسم رواية من تأليف الأديب الجزائري واسيني الأعرج"
            },
            {
                "clue_2)": "مادة تستخرج من ماء البحر"
            }
        ]
    },
    {
        "direction": "horizontal",
        "clue_number": "3",
        "clues": [
            {
                "clue_1)": "طَري , ليّن"
            },
            {
                "clue_2)": "للندبة"
            },
            {
                "clue_3)": "دولة عربية تقع في منطقة القرن الأفريقي"
            }
        ]
    },
    {
        "direction": "horizontal",
        "clue_number": "4",
        "clues": [
            {
                "clue_1)": "من أغاني أم كلثوم كلمات أحمد رامي وألحان سيد مكاوي"
            },
            {
                "clue_2)": "نوع مِنْ نَسِيج الحَرِير أو الدِّيبَاج"
            }
        ]
    },
    {
        "direction": "horizontal",
        "clue_number": "5",
        "clues": [
            {
                "clue_1)": "أحلى"
            },
            {
                "clue_2)": "ضَعْف"
            },
            {
                "clue_3)": "اليابسة ( معكوسة )"
            }
        ]
    },
    {
        "direction": "horizontal",
        "clue_number": "6",
        "clues": [
            {
                "clue_1)": "للتمنّي"
            },
            {
                "clue_2)": "أنشِئ , أشَكّل"
            },
            {
                "clue_3)": "قِلادة من معدن تُمنح للفائز بسباق أو مباراة"
            }
        ]
    },
    {
        "direction": "horizontal",
        "clue_number": "7",
        "clues": [
            {
                "clue_1)": "نسّقَها ( معكوسة )"
            },
            {
                "clue_2)": "مُمْتَلِئ البَطْنُ بِالطَّعَام"
            },
            {
                "clue_3)": "للتعريف"
            }
        ]
    },
    {
        "direction": "horizontal",
        "clue_number": "8",
        "clues": [
            {
                "clue_1)": "إحدى مسرحيات دريد لحام"
            },
            {
                "clue_2)": "من أنواع الألبسة"
            }
        ]
    },
    {
        "direction": "horizontal",
        "clue_number": "9",
        "clues": [
            {
                "clue_1)": "حُبوب تُصنع منها القهوة"
            },
            {
                "clue_2)": "والدتي"
            },
            {
                "clue_3)": "سعة وزيادة ووفرة"
            }
        ]
    },
    {
        "direction": "horizontal",
        "clue_number": "10",
        "clues": [
            {
                "clue_1)": "من أجمل مؤلفات المعري في النثر"
            },
            {
                "clue_2)": "اجتهدَ وثابرَ"
            }
        ]
    },
    {
        "direction": "horizontal",
        "clue_number": "11",
        "clues": [
            {
                "clue_1)": "قمح"
            },
            {
                "clue_2)": "مَنْ يقوم بإيقاظ الناس لتناول السَّحور خلال شهر رمضان"
            },
            {
                "clue_3)": "ظرف أو وضْع"
            }
        ]
    },
    {
        "direction": "horizontal",
        "clue_number": "12",
        "clues": [
            {
                "clue_1)": "عكس رِبْح ( معكوسة )"
            },
            {
                "clue_2)": "تنصب الفعل المضارع"
            },
            {
                "clue_3)": "عاصمة الشيشان"
            }
        ]
    },
    {
        "direction": "horizontal",
        "clue_number": "13",
        "clues": [
            {
                "clue_1)": "إحدى دول أمريكا الوسطى"
            },
            {
                "clue_2)": "وَبّخَ"
            }
        ]
    },
    {
        "direction": "horizontal",
        "clue_number": "14",
        "clues": [
            {
                "clue_1)": "غشّاش , مُحتال"
            },
            {
                "clue_2)": "عالم رياضيات وفلك وفيلسوف يوناني أحد الحكماء السبعة"
            },
            {
                "clue_3)": "سقي"
            }
        ]
    },
    {
        "direction": "horizontal",
        "clue_number": "15",
        "clues": [
            {
                "clue_1)": "محمد ... ..... لاعب كرة قدم مصري معتزل"
            },
            {
                "clue_2)": "يُسانِدان"
            }
        ]
    }
]