[
    {
        "direction": "vertical",
        "clue_number": "15",
        "clues": [
            {
                "clue_1)": "غير ناضج"
            },
            {
                "clue_2)": "يقرع الجرس"
            },
            {
                "clue_3)": "أموال"
            },
            {
                "clue_4)": "أكبر الطيور الجوارح"
            }
        ]
    },
    {
        "direction": "vertical",
        "clue_number": "14",
        "clues": [
            {
                "clue_1)": "التقويم الذي يعتمد على دورة القمر لتحديد الأشهر"
            }
        ]
    },
    {
        "direction": "vertical",
        "clue_number": "13",
        "clues": [
            {
                "clue_1)": "شاعر غزل عربي من أهل الحجاز أطلق عليه لقب مجنون لبنى"
            },
            {
                "clue_2)": "فيل ضخم منقرض"
            }
        ]
    },
    {
        "direction": "vertical",
        "clue_number": "12",
        "clues": [
            {
                "clue_1)": "واسِع"
            },
            {
                "clue_2)": "ما اجتمَع من الأشياء وتكوّم بعضُه فوق بعض , أو الأنقاض ( معكوسة )"
            },
            {
                "clue_3)": "الاسم الأول لشاعرة عراقية راحلة"
            }
        ]
    },
    {
        "direction": "vertical",
        "clue_number": "11",
        "clues": [
            {
                "clue_1)": "من أنواع السفن الحربية"
            },
            {
                "clue_2)": "اسم شعب من السكان الأصليين للبرازيل الذين يعيشون في غابات الأمازون"
            },
            {
                "clue_3)": "فاكهة ذكرت في القرآن الكريم"
            }
        ]
    },
    {
        "direction": "vertical",
        "clue_number": "10",
        "clues": [
            {
                "clue_1)": "ركائز"
            },
            {
                "clue_2)": "الماء علا الشيء وغطّاه"
            },
            {
                "clue_3)": "مدينة يمنية"
            }
        ]
    },
    {
        "direction": "vertical",
        "clue_number": "9",
        "clues": [
            {
                "clue_1)": "أهل البادية وسكَّانها"
            },
            {
                "clue_2)": "للنهي"
            },
            {
                "clue_3)": "أشخاص معروفون على نطاق واسع"
            }
        ]
    },
    {
        "direction": "vertical",
        "clue_number": "8",
        "clues": [
            {
                "clue_1)": "الحنَفِيَّة ( معكوسة )"
            },
            {
                "clue_2)": "تنتمي إلى إحدى الدول العربية الآسيوية"
            }
        ]
    },
    {
        "direction": "vertical",
        "clue_number": "7",
        "clues": [
            {
                "clue_1)": "روائي جزائري من مؤلفاته : مملكة الفراشة , والبيت الأندلسي"
            }
        ]
    },
    {
        "direction": "vertical",
        "clue_number": "6",
        "clues": [
            {
                "clue_1)": "اجتماعٌ للناس على فرح ومسرّة ( معكوسة )"
            },
            {
                "clue_2)": "عاصمة استراليا"
            }
        ]
    },
    {
        "direction": "vertical",
        "clue_number": "5",
        "clues": [
            {
                "clue_1)": "الجزء في النَّبات الذي يتكوّن فيه الحَبّ"
            },
            {
                "clue_2)": "عاصمة الهند"
            }
        ]
    },
    {
        "direction": "vertical",
        "clue_number": "4",
        "clues": [
            {
                "clue_1)": "علم مذكر معناه النّصيب أو ذو الوجه الحَسن"
            },
            {
                "clue_2)": "أغصان الشجرة"
            }
        ]
    },
    {
        "direction": "vertical",
        "clue_number": "3",
        "clues": [
            {
                "clue_1)": "عملة جنوب إفريقيا"
            },
            {
                "clue_2)": "طعام من خبزٍ مفتوت ولَحْم ومَرَق"
            },
            {
                "clue_3)": "علقم"
            },
            {
                "clue_4)": "للتعريف"
            }
        ]
    },
    {
        "direction": "vertical",
        "clue_number": "2",
        "clues": [
            {
                "clue_1)": "أكبر المحافظات المصرية من حيث المساحة"
            },
            {
                "clue_2)": "اسم موصول"
            }
        ]
    },
    {
        "direction": "vertical",
        "clue_number": "1",
        "clues": [
            {
                "clue_1)": "كان يُطلق عليه قديماً اسم الكَحّال"
            },
            {
                "clue_2)": "أداة تستخدم لرمي السهام"
            }
        ]
    },
    {
        "direction": "horizontal",
        "clue_number": "1",
        "clues": [
            {
                "clue_1)": "ملحن ومغني ومؤلف أغاني أطفال سوري من أصل جزائري له الكثير من الأعمال الموسيقية في الرسوم المتحركة المدبلجة"
            }
        ]
    },
    {
        "direction": "horizontal",
        "clue_number": "2",
        "clues": [
            {
                "clue_1)": "السّارِق , النّاهِب ( معكوسة )"
            },
            {
                "clue_2)": "حُب"
            },
            {
                "clue_3)": "سَفَري"
            }
        ]
    },
    {
        "direction": "horizontal",
        "clue_number": "3",
        "clues": [
            {
                "clue_1)": "منظمة الأمم المتحدة للطفولة"
            },
            {
                "clue_2)": "عاصمة المَجَر"
            }
        ]
    },
    {
        "direction": "horizontal",
        "clue_number": "4",
        "clues": [
            {
                "clue_1)": "اسم يُطلق على لعبة كرة الريشة الطائرة"
            },
            {
                "clue_2)": "أحصى"
            },
            {
                "clue_3)": "ظَلّ"
            }
        ]
    },
    {
        "direction": "horizontal",
        "clue_number": "5",
        "clues": [
            {
                "clue_1)": "أمر فظيع"
            },
            {
                "clue_2)": "الصّديق ( معكوسة )"
            },
            {
                "clue_3)": "كُوَّة أَو نافذة صغِيرة يدخل منها النور"
            }
        ]
    },
    {
        "direction": "horizontal",
        "clue_number": "6",
        "clues": [
            {
                "clue_1)": "أحد الألقاب التي أطلقت على نور الدين زنكي"
            },
            {
                "clue_2)": "تجويف في القسم الأعلى من القلب يستقبل الدَّم من الأوردة"
            }
        ]
    },
    {
        "direction": "horizontal",
        "clue_number": "7",
        "clues": [
            {
                "clue_1)": "عالِمة"
            },
            {
                "clue_2)": "للنداء"
            },
            {
                "clue_3)": "الجُود"
            }
        ]
    },
    {
        "direction": "horizontal",
        "clue_number": "8",
        "clues": [
            {
                "clue_1)": "يَرِق ويَحِن"
            },
            {
                "clue_2)": "1000 كيلوغرام"
            },
            {
                "clue_3)": "انتسبَ بِصِلة أو قرابة"
            },
            {
                "clue_4)": "علم مذكر معناه : الذي شرب حتى ارتوى"
            }
        ]
    },
    {
        "direction": "horizontal",
        "clue_number": "9",
        "clues": [
            {
                "clue_1)": "النفس الباطنة بما تضمُّ من إحساسات"
            },
            {
                "clue_2)": "نباتُ يُغْلَى ورقُهُ ويشرب ( معكوسة )"
            },
            {
                "clue_3)": "ما يوضَع من حلي في الأذن"
            }
        ]
    },
    {
        "direction": "horizontal",
        "clue_number": "10",
        "clues": [
            {
                "clue_1)": "نظير"
            },
            {
                "clue_2)": "أكبر دولة في أمريكا الوسطى"
            },
            {
                "clue_3)": "ضمير منفصل"
            }
        ]
    },
    {
        "direction": "horizontal",
        "clue_number": "11",
        "clues": [
            {
                "clue_1)": "بحر"
            },
            {
                "clue_2)": "أبوهما"
            },
            {
                "clue_3)": "عِزّة وشرف"
            }
        ]
    },
    {
        "direction": "horizontal",
        "clue_number": "12",
        "clues": [
            {
                "clue_1)": "قضاء يَقضي به الله على عباده"
            },
            {
                "clue_2)": "اسم جارية وشاعرة ومغنية من العصر العباسي"
            },
            {
                "clue_3)": "لَظى"
            }
        ]
    },
    {
        "direction": "horizontal",
        "clue_number": "13",
        "clues": [
            {
                "clue_1)": "اسم يُطلَق على الجمل والنَّاقة"
            },
            {
                "clue_2)": "قَول آمين بعد الدعاء"
            }
        ]
    },
    {
        "direction": "horizontal",
        "clue_number": "14",
        "clues": [
            {
                "clue_1)": "ارتفعَ"
            },
            {
                "clue_2)": "جمع هِر"
            },
            {
                "clue_3)": "اختصار المنظمة الدولية للمعايير"
            }
        ]
    },
    {
        "direction": "horizontal",
        "clue_number": "15",
        "clues": [
            {
                "clue_1)": "السُّور من شوك أو حائط أو أسلاك"
            },
            {
                "clue_2)": "مؤرخ ومفسّر وفقيه مؤلف موسوعة البداية والنهاية"
            }
        ]
    }
]