[
    {
        "direction": "vertical",
        "clue_number": "15",
        "clues": [
            {
                "clue_1)": "مثل يدل على أن من يتمهل ويتروى ويفكر قبل أن يعمل سوف يحصل على ما يريد ويبتغي"
            }
        ]
    },
    {
        "direction": "vertical",
        "clue_number": "14",
        "clues": [
            {
                "clue_1)": "شهر هجري"
            },
            {
                "clue_2)": "نظير"
            },
            {
                "clue_3)": "بطل شُجاع"
            }
        ]
    },
    {
        "direction": "vertical",
        "clue_number": "13",
        "clues": [
            {
                "clue_1)": "أديب وموسوعي ومؤرخ لبناني ألّف أول موسوعة عربية سمّاها دائرة المعارف (معكوسة)"
            }
        ]
    },
    {
        "direction": "vertical",
        "clue_number": "12",
        "clues": [
            {
                "clue_1)": "أَصْلَحَ الثوب بِضَمِّ بَعْضِه إلى بَعْض بِالخِياطَة"
            },
            {
                "clue_2)": "للندبة"
            },
            {
                "clue_3)": "كَرَمي"
            },
            {
                "clue_4)": "نَظَر بتَحْديق"
            }
        ]
    },
    {
        "direction": "vertical",
        "clue_number": "11",
        "clues": [
            {
                "clue_1)": "مَن يُوَزِّعُ الرَّسائِل والطُّرود على أَصْحابِها"
            },
            {
                "clue_2)": "من أطوار القمر"
            }
        ]
    },
    {
        "direction": "vertical",
        "clue_number": "10",
        "clues": [
            {
                "clue_1)": "جمع الرّوح"
            },
            {
                "clue_2)": "هواء متحرك ( بصيغة الجمع )"
            }
        ]
    },
    {
        "direction": "vertical",
        "clue_number": "9",
        "clues": [
            {
                "clue_1)": "الذي حِرفته الصَّقْل والتلميع"
            },
            {
                "clue_2)": "وارى في التراب"
            },
            {
                "clue_3)": "لُعاب"
            }
        ]
    },
    {
        "direction": "vertical",
        "clue_number": "8",
        "clues": [
            {
                "clue_1)": "ولاية أمريكية"
            },
            {
                "clue_2)": "من وحدات قياس الطول تساوي 2.54 سنتيمتر ( مُعرّفة )"
            }
        ]
    },
    {
        "direction": "vertical",
        "clue_number": "7",
        "clues": [
            {
                "clue_1)": "قادِم (معكوسة)"
            },
            {
                "clue_2)": "غُبار أسود"
            },
            {
                "clue_3)": "رمز رياضي"
            },
            {
                "clue_4)": "والدة"
            }
        ]
    },
    {
        "direction": "vertical",
        "clue_number": "6",
        "clues": [
            {
                "clue_1)": "دولة آسيوية عاصمتها مانيلا"
            },
            {
                "clue_2)": "جبل صغير"
            },
            {
                "clue_3)": "علم مذكر معناه ذو المجد"
            }
        ]
    },
    {
        "direction": "vertical",
        "clue_number": "5",
        "clues": [
            {
                "clue_1)": "يبدأ في 21 آذار من كل عام"
            },
            {
                "clue_2)": "مدينة يمنية"
            }
        ]
    },
    {
        "direction": "vertical",
        "clue_number": "4",
        "clues": [
            {
                "clue_1)": "من أسماء الرسول صلّى الله عليه وسلّم"
            },
            {
                "clue_2)": "المضمون"
            }
        ]
    },
    {
        "direction": "vertical",
        "clue_number": "3",
        "clues": [
            {
                "clue_1)": "حرفان مكرران"
            },
            {
                "clue_2)": "علم مؤنث معناه جمع أمنية"
            },
            {
                "clue_3)": "الأضخم , الأعظم"
            }
        ]
    },
    {
        "direction": "vertical",
        "clue_number": "2",
        "clues": [
            {
                "clue_1)": "عاتبَ"
            },
            {
                "clue_2)": "عاصمة الصين"
            },
            {
                "clue_3)": "جمع سَلّة (معكوسة)"
            }
        ]
    },
    {
        "direction": "vertical",
        "clue_number": "1",
        "clues": [
            {
                "clue_1)": "الشواطئ"
            },
            {
                "clue_2)": "الكثير الكذب والإفك"
            }
        ]
    },
    {
        "direction": "horizontal",
        "clue_number": "1",
        "clues": [
            {
                "clue_1)": "سورة قرآنية معناها الملائكةُ المصطفّون"
            },
            {
                "clue_2)": "حبس"
            },
            {
                "clue_3)": "استنشقَ"
            }
        ]
    },
    {
        "direction": "horizontal",
        "clue_number": "2",
        "clues": [
            {
                "clue_1)": "الطين اليابس (معكوسة)"
            },
            {
                "clue_2)": "المادة المخدّرة التي تستخرج من ثمرة الخشخاش"
            }
        ]
    },
    {
        "direction": "horizontal",
        "clue_number": "3",
        "clues": [
            {
                "clue_1)": "مادة قاتلة"
            },
            {
                "clue_2)": "غِلاف مِن الوَرق الْمُقَوَّى تُوضَع فيه أَوْراق ووَثائق بِها مَواضيع مُعَيَّنَة"
            },
            {
                "clue_3)": "المساعَدات"
            }
        ]
    },
    {
        "direction": "horizontal",
        "clue_number": "4",
        "clues": [
            {
                "clue_1)": "مطربة سورية"
            },
            {
                "clue_2)": "للاستثناء"
            }
        ]
    },
    {
        "direction": "horizontal",
        "clue_number": "5",
        "clues": [
            {
                "clue_1)": "المُبتغى , المُراد"
            },
            {
                "clue_2)": "قرعوا الجرس"
            }
        ]
    },
    {
        "direction": "horizontal",
        "clue_number": "6",
        "clues": [
            {
                "clue_1)": "دولة غير ساحلية تقع وسط إفريقيا عاصمتها بانجي"
            }
        ]
    },
    {
        "direction": "horizontal",
        "clue_number": "7",
        "clues": [
            {
                "clue_1)": "اسم محبوبة الشاعر قيس بن ذريح"
            }
        ]
    },
    {
        "direction": "horizontal",
        "clue_number": "8",
        "clues": [
            {
                "clue_1)": "حرف نصب يفيد التعليل"
            },
            {
                "clue_2)": "حرف نصب"
            },
            {
                "clue_3)": "خاصتنا"
            }
        ]
    },
    {
        "direction": "horizontal",
        "clue_number": "9",
        "clues": [
            {
                "clue_1)": "إستناد , إتّكال"
            },
            {
                "clue_2)": "يُناقش"
            }
        ]
    },
    {
        "direction": "horizontal",
        "clue_number": "10",
        "clues": [
            {
                "clue_1)": "أحصل على"
            },
            {
                "clue_2)": "جَنّة , بُستان"
            }
        ]
    },
    {
        "direction": "horizontal",
        "clue_number": "11",
        "clues": [
            {
                "clue_1)": "للجزم"
            },
            {
                "clue_2)": "مُذنِب , مُجرِم"
            },
            {
                "clue_3)": "مَن لم تنبت له لحية (معكوسة)"
            }
        ]
    },
    {
        "direction": "horizontal",
        "clue_number": "12",
        "clues": [
            {
                "clue_2)": "تضع عليها الغطاء (معكوسة)"
            }
        ]
    },
    {
        "direction": "horizontal",
        "clue_number": "13",
        "clues": [
            {
                "clue_1)": "لزوم المسجد لطاعة الله والتفرغ للعبادة في الليل أو النهار (معكوسة)"
            },
            {
                "clue_2)": "أسافِر"
            },
            {
                "clue_3)": "طائر يُضْرَب بِه الْمَثَل فِي الشُّؤْم"
            }
        ]
    },
    {
        "direction": "horizontal",
        "clue_number": "14",
        "clues": [
            {
                "clue_1)": "من أشهر العلماء المسلمين في الفلك والرياضيات"
            },
            {
                "clue_2)": "والد"
            },
            {
                "clue_3)": "أصدر المريض صوتاً"
            }
        ]
    },
    {
        "direction": "horizontal",
        "clue_number": "15",
        "clues": [
            {
                "clue_1)": "لقب كان يطلق على ملوك الفُرس"
            },
            {
                "clue_2)": "من ألقاب مدينة نابلس في فلسطين"
            }
        ]
    }
]